{
  "version": "4.6.0",
  "flags": {},
  "shapes": [
    {
      "label": "det_11",
      "points": [
        [
          3.0,
          0.0
        ],
        [
          264.51612903225805,
          223.09677419354836
        ]
      ],
      "group_id": null,
      "shape_type": "rectangle",
      "flags": {}
    },
    {
      "label": "det_1",
      "points": [
        [
          261.93548387096774,
          23.741935483870975
        ],
        [
          503.22580645161287,
          224.38709677419354
        ]
      ],
      "group_id": null,
      "shape_type": "rectangle",
      "flags": {}
    },
    {
      "label": "det_1",
      "points": [
        [
          498.06451612903226,
          24.387096774193537
        ],
        [
          733.5483870967741,
          227.61290322580646
        ]
      ],
      "group_id": null,
      "shape_type": "rectangle",
      "flags": {}
    },
    {
      "label": "det_1",
      "points": [
        [
          732.258064516129,
          26.967741935483872
        ],
        [
          966.4516129032257,
          234.06451612903226
        ]
      ],
      "group_id": null,
      "shape_type": "rectangle",
      "flags": {}
    },
    {
      "label": "det_3",
      "points": [
        [
          958.7096774193548,
          28.903225806451616
        ],
        [
          1182.0,
          243.0
        ]
      ],
      "group_id": null,
      "shape_type": "rectangle",
      "flags": {}
    },
    {
      "label": "det_4",
      "points": [
        [
          1181.2903225806451,
          35.35483870967741
        ],
        [
          1370.0,
          243.0
        ]
      ],
      "group_id": null,
      "shape_type": "rectangle",
      "flags": {}
    },
    {
      "label": "det_5",
      "points": [
        [
          1354.8387096774193,
          45.67741935483869
        ],
        [
          1574.0,
          242.0
        ]
      ],
      "group_id": null,
      "shape_type": "rectangle",
      "flags": {}
    },
    {
      "label": "det_10",
      "points": [
        [
          1575.483870967742,
          26.967741935483872
        ],
        [
          1810.0,
          243.0
        ]
      ],
      "group_id": null,
      "shape_type": "rectangle",
      "flags": {}
    },
    {
      "label": "det_7",
      "points": [
        [
          1805.1612903225805,
          44.38709677419354
        ],
        [
          1998.2903225806451,
          245.03225806451613
        ]
      ],
      "group_id": null,
      "shape_type": "rectangle",
      "flags": {}
    },
    {
      "label": "det_42",
      "points": [
        [
          1998.0645161290322,
          26.967741935483872
        ],
        [
          2217.9245283018868,
          239.15094339622635
        ]
      ],
      "group_id": null,
      "shape_type": "rectangle",
      "flags": {}
    }
  ],
  "imagePath": "det_5.png",
  "imageData": null,
  "imageHeight": 244,
  "imageWidth": 2219,
  "expected_pla_n": {
    "seq": [
      "det_11",
      "det_1",
      "det_3",
      "det_4",
      "det_5",
      "det_10",
      "det_7",
      "det_42"
    ],
    "qt": [
      1,
      3,
      1,
      1,
      1,
      1,
      1,
      1
    ]
  },
  "item_match": [
    "det_11 matched",
    "det_1 matched",
    "det_3 matched",
    "det_4 matched",
    "det_5 matched",
    "det_10 matched",
    "det_7 matched",
    "det_42 matched"
  ],
  "quantity_match": [
    "det_11 matched",
    "det_1 matched",
    "det_3 matched",
    "det_4 matched",
    "det_5 matched",
    "det_10 matched",
    "det_7 matched",
    "det_42 matched"
  ],
  "overall_quantitiy_match_ratio": 100
}